<?xml version="1.0"?>
<config>
    <acl>
        <resources>
            <admin>
                <children>
                    <system>
                        <children>
                            <config>
                                <children>
                                    <sphinxsearch translate="title" module="sphinxsearch">
                                        <title>Sphinx Search</title>
                                    </sphinxsearch>
                                </children>
                            </config>
                        </children>
                    </system>
                </children>
            </admin>
        </resources>
    </acl>
</config>